kamonohashi/__init__.py
kamonohashi/cli/__init__.py
kamonohashi/cli/account.py
kamonohashi/cli/configuration.py
kamonohashi/cli/data.py
kamonohashi/cli/data_set.py
kamonohashi/cli/inference.py
kamonohashi/cli/kqi.py
kamonohashi/cli/notebook.py
kamonohashi/cli/object_storage.py
kamonohashi/cli/pprint.py
kamonohashi/cli/preprocessing.py
kamonohashi/cli/tenant.py
kamonohashi/cli/training.py
kamonohashi/cli/util.py
kamonohashi_cli-4.0.2.dist-info/DESCRIPTION.rst
kamonohashi_cli-4.0.2.dist-info/METADATA
kamonohashi_cli-4.0.2.dist-info/RECORD
kamonohashi_cli-4.0.2.dist-info/WHEEL
kamonohashi_cli-4.0.2.dist-info/entry_points.txt
kamonohashi_cli-4.0.2.dist-info/metadata.json
kamonohashi_cli-4.0.2.dist-info/top_level.txt
