Metadata-Version: 2.0
Name: kamonohashi-cli
Version: 4.0.2
Summary: KAMONOHASHI Command Line Interface
Home-page: https://github.com/KAMONOHASHI/kamonohashi
Author: NS Solutions Corporation
Author-email: kamonohashi-support@jp.nssol.nipponsteel.com
License: Apache License 2.0
Platform: UNKNOWN
Requires-Dist: click (>=7.1.1)
Requires-Dist: kamonohashi-sdk (==4.0.2)
Requires-Dist: six (>=1.10)
Requires-Dist: urllib3 (>=1.23)
